pocketsmith_mcp/__init__.py
pocketsmith_mcp/__main__.py
pocketsmith_mcp/config.py
pocketsmith_mcp/errors.py
pocketsmith_mcp/logger.py
pocketsmith_mcp/server.py
pocketsmith_mcp/client/__init__.py
pocketsmith_mcp/client/api_client.py
pocketsmith_mcp/client/circuit_breaker.py
pocketsmith_mcp/client/rate_limiter.py
pocketsmith_mcp/client/retry.py
pocketsmith_mcp/models/__init__.py
pocketsmith_mcp/models/account.py
pocketsmith_mcp/models/attachment.py
pocketsmith_mcp/models/category.py
pocketsmith_mcp/models/common.py
pocketsmith_mcp/models/event.py
pocketsmith_mcp/models/institution.py
pocketsmith_mcp/models/transaction.py
pocketsmith_mcp/models/user.py
pocketsmith_mcp/tools/__init__.py
pocketsmith_mcp/tools/accounts.py
pocketsmith_mcp/tools/attachments.py
pocketsmith_mcp/tools/budgeting.py
pocketsmith_mcp/tools/categories.py
pocketsmith_mcp/tools/events.py
pocketsmith_mcp/tools/institutions.py
pocketsmith_mcp/tools/labels.py
pocketsmith_mcp/tools/transaction_accounts.py
pocketsmith_mcp/tools/transactions.py
pocketsmith_mcp/tools/users.py
pocketsmith_mcp/tools/utilities.py
pocketsmith_mcp-1.0.1.dist-info/METADATA
pocketsmith_mcp-1.0.1.dist-info/WHEEL
pocketsmith_mcp-1.0.1.dist-info/entry_points.txt
pocketsmith_mcp-1.0.1.dist-info/licenses/LICENSE
pocketsmith_mcp-1.0.1.dist-info/RECORD
